{
  "id": "prt_cbbe6da16001UND5dIiYWdfNLs",
  "messageID": "msg_cbbe5e460001lipC2GGwAx2qyd",
  "sessionID": "ses_3610c85d4ffeyQoC4J9ft8WIfG",
  "type": "tool",
  "tool": "read",
  "callID": "toolu_vrtx_01TKK9if9k9jfM8qx99y3Hd4",
  "state": {
    "status": "completed",
    "input": {
      "filePath": "/home/user/sandbox/workspace/frontend/src/pages/RelaySwap.tsx",
      "offset": 2000,
      "limit": 120
    },
    "output": "<file>\n02001| \n02002|       console.log('Getting fresh batch swap quote for execution:', origins.length, 'tokens')\n02003| \n02004|       const multiQuote = await relayAPI.getMultiInputQuote({\n02005|         user: address,\n02006|         origins,\n02007|         destinationCurrency: batchToToken.address,\n02008|         destinationChainId: batchToChain.id,\n02009|         tradeType: 'EXACT_INPUT',\n02010|         recipient: execBatchRecipient,\n02011|       })\n02012| \n02013|       console.log('Fresh batch quote received:', multiQuote)\n02014|       console.log('Steps in quote:', multiQuote.steps.map(s => ({ id: s.id, kind: s.kind, itemCount: s.items?.length })))\n02015| \n02016|       const { sendTransaction: sendTx, waitForTransactionReceipt } = await import('wagmi/actions')\n02017|       const { wagmiConfig } = await import('@/lib/blockchain/wagmi')\n02018|       const { createPublicClient: mkClient, http: mkHttp, defineChain: mkChain } = await import('viem')\n02019| \n02020|       // Build a public client using the Relay chain's own RPC for accurate gas estimation.\n02021|       // This works even for chains not in wagmiConfig.\n02022|       const chainDef = mkChain({\n02023|         id: batchChain.id,\n02024|         name: batchChain.displayName,\n02025|         nativeCurrency: {\n02026|           name: batchChain.currency.name,\n02027|           symbol: batchChain.currency.symbol,\n02028|           decimals: batchChain.currency.decimals,\n02029|         },\n02030|         rpcUrls: { default: { http: [batchChain.httpRpcUrl] } },\n02031|       })\n02032|       const publicClient = mkClient({ chain: chainDef, transport: mkHttp(batchChain.httpRpcUrl) })\n02033| \n02034|       // Collect ALL transaction-kind steps in order (approve, deposit, swap, etc.)\n02035|       const txSteps: Array<{\n02036|         stepId: string\n02037|         stepLabel: string\n02038|         to: `0x${string}`\n02039|         data: `0x${string}`\n02040|         value: bigint\n02041|         checkEndpoint?: string\n02042|       }> = []\n02043| \n02044|       for (const step of multiQuote.steps) {\n02045|         if (step.kind !== 'transaction' || !step.items?.length) continue\n02046|         for (const item of step.items) {\n02047|           const d = item.data\n02048|           txSteps.push({\n02049|             stepId: step.id,\n02050|             stepLabel: step.id === 'approve' ? 'Approval' : step.id === 'deposit' ? 'Deposit' : step.action || step.id,\n02051|             to: d.to as `0x${string}`,\n02052|             data: d.data as `0x${string}`,\n02053|             // Relay sometimes sends '0x0' or missing value — normalise to 0n\n02054|             value: d.value && d.value !== '0x0' ? BigInt(d.value) : 0n,\n02055|             checkEndpoint: item.check?.endpoint,\n02056|           })\n02057|         }\n02058|       }\n02059| \n02060|       console.log('Total tx steps to execute:', txSteps.length, txSteps.map(s => s.stepId))\n02061| \n02062|       if (txSteps.length === 0) {\n02063|         toast.error('No transactions to execute in quote.')\n02064|         setIsSwapping(false)\n02065|         return\n02066|       }\n02067| \n02068|       // Estimate gas for every step using the chain's RPC before prompting any signatures.\n02069|       // We deliberately do NOT pass maxFeePerGas/maxPriorityFeePerGas from the Relay quote —\n02070|       // those values are stale by the time the user signs and cause wallets to show inflated fees.\n02071|       // Letting the wallet/node pick current gas prices is always more accurate.\n02072|       const gasLimits = await Promise.all(\n02073|         txSteps.map(async (step) => {\n02074|           try {\n02075|             const estimated = await publicClient.estimateGas({\n02076|               account: address as `0x${string}`,\n02077|               to: step.to,\n02078|               data: step.data,\n02079|               value: step.value,\n02080|             })\n02081|             return (estimated * 130n) / 100n  // 1.3x buffer\n02082|           } catch (e) {\n02083|             console.warn(`Gas estimation failed for step ${step.stepId}:`, e)\n02084|             return undefined\n02085|           }\n02086|         })\n02087|       )\n02088| \n02089|       toast.info(`Executing ${txSteps.length} step(s)...`)\n02090| \n02091|       let confirmedCount = 0\n02092|       const failedTxs: number[] = []\n02093| \n02094|       for (let i = 0; i < txSteps.length; i++) {\n02095|         const step = txSteps[i]\n02096|         console.log(`Step ${i + 1}/${txSteps.length}: ${step.stepId}`, {\n02097|           to: step.to,\n02098|           value: step.value.toString(),\n02099|           gas: gasLimits[i]?.toString(),\n02100|         })\n02101|         try {\n02102|           const hash = await sendTx(wagmiConfig, {\n02103|             to: step.to,\n02104|             data: step.data,\n02105|             value: step.value,\n02106|             gas: gasLimits[i],\n02107|             // Explicitly omit maxFeePerGas / maxPriorityFeePerGas so the wallet\n02108|             // uses current network prices instead of the stale values from the quote\n02109|           })\n02110|           console.log(`Step ${i + 1} (${step.stepId}) submitted:`, hash)\n02111|           toast.info(`${step.stepLabel} ${i + 1}/${txSteps.length} submitted...`)\n02112| \n02113|           // Wait for on-chain confirmation\n02114|           await waitForTransactionReceipt(wagmiConfig, { hash })\n02115|           confirmedCount++\n02116|           console.log(`Step ${i + 1} (${step.stepId}) confirmed`)\n02117| \n02118|           // After an approve, wait briefly for the allowance to propagate before\n02119|           // sending the deposit — otherwise the deposit reverts on the allowance check\n02120|           if (step.stepId === 'approve') {\n\n(File has more lines. Use 'offset' parameter to read beyond line 2120)\n</file>",
    "metadata": {
      "preview": "\n      console.log('Getting fresh batch swap quote for execution:', origins.length, 'tokens')\n\n      const multiQuote = await relayAPI.getMultiInputQuote({\n        user: address,\n        origins,\n        destinationCurrency: batchToToken.address,\n        destinationChainId: batchToChain.id,\n        tradeType: 'EXACT_INPUT',\n        recipient: execBatchRecipient,\n      })\n\n      console.log('Fresh batch quote received:', multiQuote)\n      console.log('Steps in quote:', multiQuote.steps.map(s => ({ id: s.id, kind: s.kind, itemCount: s.items?.length })))\n\n      const { sendTransaction: sendTx, waitForTransactionReceipt } = await import('wagmi/actions')\n      const { wagmiConfig } = await import('@/lib/blockchain/wagmi')\n      const { createPublicClient: mkClient, http: mkHttp, defineChain: mkChain } = await import('viem')\n\n      // Build a public client using the Relay chain's own RPC for accurate gas estimation."
    },
    "title": "frontend/src/pages/RelaySwap.tsx",
    "time": {
      "start": 1772678994818,
      "end": 1772678994820
    }
  }
}