{
  "id": "prt_b7412f775001haklX2shEcaSGX",
  "messageID": "msg_b741176a3001fJm6UHNXQHM0ac",
  "sessionID": "ses_48c2723c4ffemhO1dVP9NSYRB5",
  "type": "tool",
  "tool": "edit",
  "callID": "toolu_vrtx_01Njky5UfVy7MMBubudbCEbz",
  "state": {
    "status": "completed",
    "input": {
      "filePath": "/home/user/sandbox/workspace/frontend/src/pages/RelaySwap.tsx",
      "oldString": "  const loadSwapHistory = async () => {\n    if (!address) return\n    \n    setIsLoadingHistory(true)\n    try {\n      const { requests } = await relayAPI.getRequests({\n        user: address,\n        limit: 20,\n        sortBy: 'createdAt',\n        sortDirection: 'desc',\n      })",
      "newString": "  const loadSwapHistory = async () => {\n    if (!address) return\n    \n    if (chains.length === 0) {\n      console.warn('Chains not loaded yet, skipping history load')\n      return\n    }\n    \n    setIsLoadingHistory(true)\n    try {\n      console.log('Loading swap history with', chains.length, 'chains available')\n      \n      const { requests } = await relayAPI.getRequests({\n        user: address,\n        limit: 20,\n        sortBy: 'createdAt',\n        sortDirection: 'desc',\n      })\n      \n      console.log('Received', requests.length, 'requests')"
    },
    "output": "<system-reminder>CRITICAL: Make sure you read the hooks functionality and the functions they expose. DON'T MAKE ASSUMPTIONS</system-reminder><system-reminder>CRITICAL: Make sure you run the diagnostics tool when you're done with all the tasks.</system-reminder>",
    "metadata": {
      "diagnostics": {},
      "diff": "Index: /home/user/sandbox/workspace/frontend/src/pages/RelaySwap.tsx\n===================================================================\n--- /home/user/sandbox/workspace/frontend/src/pages/RelaySwap.tsx\n+++ /home/user/sandbox/workspace/frontend/src/pages/RelaySwap.tsx\n@@ -1481,17 +1481,26 @@\n \n const loadSwapHistory = async () => {\n   if (!address) return\n   \n+  if (chains.length === 0) {\n+    console.warn('Chains not loaded yet, skipping history load')\n+    return\n+  }\n+  \n   setIsLoadingHistory(true)\n   try {\n+    console.log('Loading swap history with', chains.length, 'chains available')\n+    \n     const { requests } = await relayAPI.getRequests({\n       user: address,\n       limit: 20,\n       sortBy: 'createdAt',\n       sortDirection: 'desc',\n     })\n     \n+    console.log('Received', requests.length, 'requests')\n+    \n     const history: SwapHistory[] = await Promise.all(requests.map(async req => {\n       console.log('=== Processing request:', req.id)\n       console.log('Request data:', {\n         inTxs: req.data.inTxs,\n"
    },
    "title": "frontend/src/pages/RelaySwap.tsx",
    "time": {
      "start": 1767178962520,
      "end": 1767178962525
    }
  }
}