{
  "id": "prt_c9f0f4f20001ApQuk5w2bvvB5l",
  "messageID": "msg_c9f0f34be001unCfbp6y77NgVE",
  "sessionID": "ses_3610c85d4ffeyQoC4J9ft8WIfG",
  "type": "tool",
  "tool": "bash",
  "callID": "toolu_vrtx_011HMLxHRLdqRAn8GcFFxU2d",
  "state": {
    "status": "completed",
    "input": {
      "command": "cd /home/user/sandbox/workspace && git log --oneline -5",
      "description": "Check current git state"
    },
    "output": "1b5ff359 Snapshot at 2026-02-27T12:23:34.171Z\n65705e57 Snapshot at 2026-02-27T12:14:12.827Z\n0493ea9f Snapshot at 2026-02-27T12:07:13.544Z\n9a3a04a5 Snapshot at 2026-02-27T12:01:16.320Z\n924b6767 Snapshot at 2026-02-27T11:56:32.493Z\n",
    "metadata": {
      "output": "1b5ff359 Snapshot at 2026-02-27T12:23:34.171Z\n65705e57 Snapshot at 2026-02-27T12:14:12.827Z\n0493ea9f Snapshot at 2026-02-27T12:07:13.544Z\n9a3a04a5 Snapshot at 2026-02-27T12:01:16.320Z\n924b6767 Snapshot at 2026-02-27T11:56:32.493Z\n",
      "exit": 0,
      "description": "Check current git state"
    },
    "title": "cd /home/user/sandbox/workspace && git log --oneline -5",
    "time": {
      "start": 1772195107540,
      "end": 1772195107543
    }
  }
}