{
  "id": "prt_c9b017ea00013zB9KLwMMHIuHe",
  "messageID": "msg_c9afeadaf001qWILr5XGk79V4e",
  "sessionID": "ses_36508ab06ffeFm8HXnVC3yjmH2",
  "type": "tool",
  "tool": "edit",
  "callID": "toolu_01GA8qvW8nsoF89bmuHazyLm",
  "state": {
    "status": "completed",
    "input": {
      "filePath": "/home/user/sandbox/workspace/frontend/src/pages/RelaySwap.tsx",
      "oldString": "                  </div>\n                </div>\n\n                {batchQuote && (\n                  <Card className=\"p-3 bg-card\">\n                    <div className=\"space-y-1.5 text-xs\">\n                      <div className=\"font-medium mb-2\">Batch Swap Summary</div>",
      "newString": "                  </div>\n                </div>\n\n                {toChain?.vmType === 'svm' && (\n                  <Card className=\"p-2 bg-muted/50 border-accent\">\n                    <div className=\"text-xs font-medium mb-1\">Solana Recipient</div>\n                    <div className=\"text-xs font-mono text-muted-foreground break-all\">\n                      {solanaAddress || 'Farcaster Solana wallet not connected'}\n                    </div>\n                  </Card>\n                )}\n\n                {batchQuote && (\n                  <Card className=\"p-3 bg-card\">\n                    <div className=\"space-y-1.5 text-xs\">\n                      <div className=\"font-medium mb-2\">Batch Swap Summary</div>"
    },
    "output": "<system-reminder>CRITICAL: Make sure you read the hooks functionality and the functions they expose. DON'T MAKE ASSUMPTIONS</system-reminder><system-reminder>CRITICAL: Make sure you run the diagnostics tool when you're done with all the tasks.</system-reminder><system-reminder>CRITICAL: Make sure you hook the wallet properly with the connect button.</system-reminder>",
    "metadata": {
      "diagnostics": {},
      "diff": "Index: /home/user/sandbox/workspace/frontend/src/pages/RelaySwap.tsx\n===================================================================\n--- /home/user/sandbox/workspace/frontend/src/pages/RelaySwap.tsx\n+++ /home/user/sandbox/workspace/frontend/src/pages/RelaySwap.tsx\n@@ -3197,8 +3197,17 @@\n     </Button>\n   </div>\n </div>\n \n+{toChain?.vmType === 'svm' && (\n+  <Card className=\"p-2 bg-muted/50 border-accent\">\n+    <div className=\"text-xs font-medium mb-1\">Solana Recipient</div>\n+    <div className=\"text-xs font-mono text-muted-foreground break-all\">\n+      {solanaAddress || 'Farcaster Solana wallet not connected'}\n+    </div>\n+  </Card>\n+)}\n+\n {batchQuote && (\n   <Card className=\"p-3 bg-card\">\n     <div className=\"space-y-1.5 text-xs\">\n       <div className=\"font-medium mb-2\">Batch Swap Summary</div>\n"
    },
    "title": "frontend/src/pages/RelaySwap.tsx",
    "time": {
      "start": 1772127095811,
      "end": 1772127095823
    }
  }
}