{
  "id": "prt_c9a143bf5001CS2K7yq9nYRxxT",
  "messageID": "msg_c9a1220e9001jWfAXwiz3F4vZT",
  "sessionID": "ses_3660e5476ffeLj1zWJ3G3zn4RC",
  "type": "text",
  "text": "Now fix the EVM batch token detection. The key issue is that `alchemy_getTokenBalances` with `'erc20'` as the second param requires a paid key — with `'demo'` it returns an error or empty. The fix is to use `DEFAULT_TOKENS` instead, or better yet use the Relay API's portfolio/balance endpoint. Actually the best approach for EVM is to use Alchemy's `alchemy_getTokenBalances` with `'DEFAULT_TOKENS'` which works with the demo key, then fall back to checking the Relay list:",
  "time": {
    "start": 1772111574929,
    "end": 1772111574929
  }
}