{
  "id": "prt_c99fcdf27001i1JdaQ9Uj3SpIu",
  "messageID": "msg_c99fbc992001jgcqwbfRRsGH5y",
  "sessionID": "ses_3660e5476ffeLj1zWJ3G3zn4RC",
  "type": "tool",
  "tool": "edit",
  "callID": "toolu_011vYLttd8nBQg3ozyCbSUSw",
  "state": {
    "status": "completed",
    "input": {
      "filePath": "/home/user/sandbox/workspace/frontend/src/pages/RelaySwap.tsx",
      "oldString": "  // Detect Solana wallet\n  useEffect(() => {\n    const detectSolanaWallet = async () => {\n      try {\n        // Check if window.solana exists (Phantom, Solflare, etc.)\n        interface SolanaWindow extends Window {\n          solana?: {\n            isConnected: boolean\n            publicKey?: { toString: () => string }\n            connect: (options?: { onlyIfTrusted?: boolean }) => Promise<{ publicKey: { toString: () => string } }>\n          }\n        }\n        \n        const solanaWallet = (window as SolanaWindow).solana\n        \n        if (solanaWallet) {\n          // Check if already connected\n          if (solanaWallet.isConnected && solanaWallet.publicKey) {\n            const pubKey = solanaWallet.publicKey.toString()\n            console.log('Solana wallet detected:', pubKey)\n            setSolanaAddress(pubKey)\n          } else {\n            // Try to connect silently\n            try {\n              const response = await solanaWallet.connect({ onlyIfTrusted: true })\n              if (response.publicKey) {\n                const pubKey = response.publicKey.toString()\n                console.log('Solana wallet connected:', pubKey)\n                setSolanaAddress(pubKey)\n              }\n            } catch (err) {\n              // User hasn't approved this site yet\n              console.log('Solana wallet not connected yet')\n            }\n          }\n        }\n      } catch (error) {\n        console.error('Error detecting Solana wallet:', error)\n      }\n    }\n\n    detectSolanaWallet()\n  }, [])",
      "newString": "  // Detect Solana wallet via Farcaster SDK\n  useEffect(() => {\n    const detectSolanaWallet = async () => {\n      try {\n        const solanaProvider = await sdk.wallet.getSolanaProvider()\n        if (solanaProvider) {\n          const result = await solanaProvider.request({ method: 'connect' })\n          if (result.publicKey) {\n            console.log('Farcaster Solana wallet connected:', result.publicKey)\n            setSolanaAddress(result.publicKey)\n          }\n        }\n      } catch (error) {\n        console.log('Farcaster Solana wallet not available:', error)\n      }\n    }\n\n    detectSolanaWallet()\n  }, [])"
    },
    "output": "<system-reminder>CRITICAL: Make sure you read the hooks functionality and the functions they expose. DON'T MAKE ASSUMPTIONS</system-reminder><system-reminder>CRITICAL: Make sure you run the diagnostics tool when you're done with all the tasks.</system-reminder><system-reminder>CRITICAL: Make sure you hook the wallet properly with the connect button.</system-reminder>",
    "metadata": {
      "diagnostics": {},
      "diff": "Index: /home/user/sandbox/workspace/frontend/src/pages/RelaySwap.tsx\n===================================================================\n--- /home/user/sandbox/workspace/frontend/src/pages/RelaySwap.tsx\n+++ /home/user/sandbox/workspace/frontend/src/pages/RelaySwap.tsx\n@@ -264,46 +264,22 @@\n useEffect(() => {\n   sdk.actions.ready().catch(() => {})\n }, [])\n \n-// Detect Solana wallet\n+// Detect Solana wallet via Farcaster SDK\n useEffect(() => {\n   const detectSolanaWallet = async () => {\n     try {\n-      // Check if window.solana exists (Phantom, Solflare, etc.)\n-      interface SolanaWindow extends Window {\n-        solana?: {\n-          isConnected: boolean\n-          publicKey?: { toString: () => string }\n-          connect: (options?: { onlyIfTrusted?: boolean }) => Promise<{ publicKey: { toString: () => string } }>\n+      const solanaProvider = await sdk.wallet.getSolanaProvider()\n+      if (solanaProvider) {\n+        const result = await solanaProvider.request({ method: 'connect' })\n+        if (result.publicKey) {\n+          console.log('Farcaster Solana wallet connected:', result.publicKey)\n+          setSolanaAddress(result.publicKey)\n         }\n       }\n-      \n-      const solanaWallet = (window as SolanaWindow).solana\n-      \n-      if (solanaWallet) {\n-        // Check if already connected\n-        if (solanaWallet.isConnected && solanaWallet.publicKey) {\n-          const pubKey = solanaWallet.publicKey.toString()\n-          console.log('Solana wallet detected:', pubKey)\n-          setSolanaAddress(pubKey)\n-        } else {\n-          // Try to connect silently\n-          try {\n-            const response = await solanaWallet.connect({ onlyIfTrusted: true })\n-            if (response.publicKey) {\n-              const pubKey = response.publicKey.toString()\n-              console.log('Solana wallet connected:', pubKey)\n-              setSolanaAddress(pubKey)\n-            }\n-          } catch (err) {\n-            // User hasn't approved this site yet\n-            console.log('Solana wallet not connected yet')\n-          }\n-        }\n-      }\n     } catch (error) {\n-      console.error('Error detecting Solana wallet:', error)\n+      console.log('Farcaster Solana wallet not available:', error)\n     }\n   }\n \n   detectSolanaWallet()\n"
    },
    "title": "frontend/src/pages/RelaySwap.tsx",
    "time": {
      "start": 1772110019442,
      "end": 1772110019452
    }
  }
}