{
  "id": "prt_cc6827950001Kb6RjRyULqvskx",
  "messageID": "msg_cc6826a5a001nrwgQYNeR4SdRQ",
  "sessionID": "ses_33bf30e3cffegGvBEG13wphmnT",
  "type": "tool",
  "tool": "bash",
  "callID": "toolu_bdrk_01Juz96xTkEt4EfDPdhZ1rGz",
  "state": {
    "status": "completed",
    "input": {
      "command": "cd /home/user/sandbox/workspace && git status && git diff --stat HEAD 2>/dev/null | head -30",
      "description": "Check git status and changed files"
    },
    "output": "HEAD detached from 65705e57\nChanges not staged for commit:\n  (use \"git add <file>...\" to update what will be committed)\n  (use \"git restore <file>...\" to discard changes in working directory)\n\tmodified:   .logs/frontend.log\n\tmodified:   .vie/data/storage/session/3c41bac9-0722-49f6-aa8c-35d336973f1f/ses_33bf30e3cffegGvBEG13wphmnT.json\n\nUntracked files:\n  (use \"git add <file>...\" to include in what will be committed)\n\t.vie/data/storage/message/ses_33bf30e3cffegGvBEG13wphmnT/msg_cc6826a28001AAXtiHdjfbAQdK.json\n\t.vie/data/storage/message/ses_33bf30e3cffegGvBEG13wphmnT/msg_cc6826a5a001nrwgQYNeR4SdRQ.json\n\t.vie/data/storage/part/msg_cc6826a28001AAXtiHdjfbAQdK/\n\t.vie/data/storage/part/msg_cc6826a5a001nrwgQYNeR4SdRQ/\n\nno changes added to commit (use \"git add\" and/or \"git commit -a\")\n .logs/frontend.log                                                    | 4 ++--\n .../ses_33bf30e3cffegGvBEG13wphmnT.json                               | 2 +-\n 2 files changed, 3 insertions(+), 3 deletions(-)\n",
    "metadata": {
      "output": "HEAD detached from 65705e57\nChanges not staged for commit:\n  (use \"git add <file>...\" to update what will be committed)\n  (use \"git restore <file>...\" to discard changes in working directory)\n\tmodified:   .logs/frontend.log\n\tmodified:   .vie/data/storage/session/3c41bac9-0722-49f6-aa8c-35d336973f1f/ses_33bf30e3cffegGvBEG13wphmnT.json\n\nUntracked files:\n  (use \"git add <file>...\" to include in what will be committed)\n\t.vie/data/storage/message/ses_33bf30e3cffegGvBEG13wphmnT/msg_cc6826a28001AAXtiHdjfbAQdK.json\n\t.vie/data/storage/message/ses_33bf30e3cffegGvBEG13wphmnT/msg_cc6826a5a001nrwgQYNeR4SdRQ.json\n\t.vie/data/storage/part/msg_cc6826a28001AAXtiHdjfbAQdK/\n\t.vie/data/storage/part/msg_cc6826a5a001nrwgQYNeR4SdRQ/\n\nno changes added to commit (use \"git add\" and/or \"git commit -a\")\n .logs/frontend.log                                                    | 4 ++--\n .../ses_33bf30e3cffegGvBEG13wphmnT.json                               | 2 +-\n 2 files changed, 3 insertions(+), 3 deletions(-)\n",
      "exit": 0,
      "description": "Check git status and changed files"
    },
    "title": "cd /home/user/sandbox/workspace && git status && git diff --stat HEAD 2>/dev/null | head -30",
    "time": {
      "start": 1772856966485,
      "end": 1772856966659
    }
  }
}