{
  "id": "prt_cc388b0ee001Y64A783IL33W6f",
  "messageID": "msg_cc388087c001KngTkUdZBCXtra",
  "sessionID": "ses_340e18f1effehpbNS7x7gjeRl5",
  "type": "tool",
  "tool": "bash",
  "callID": "toolu_vrtx_01Xx5qnGkZ3BYaJzbnzgDGsv",
  "state": {
    "status": "completed",
    "input": {
      "command": "node -e \"\n// So hexToBigInt('995010715204139091') === BigInt('995010715204139091') = true\n// That means viem's hexToBigInt actually handles decimal strings correctly for this case\n// The value field is fine. Let me check what the SDK does vs what we do\n\n// SDK: hexToBigInt(stepData.value || 0)  \n// Our code: hexToBigInt(((stepItem.data.value as string) || '0') as hex)\n\n// The issue must be something else. Let me check if the approval tx is failing\n// because of the 'to' address or 'data' field\n\n// What does the approval step look like?\n// 'to' = RelayApprover contract address\n// 'data' = encoded approve() call\n// 'value' = '0' (approvals don't send ETH)\n\n// If our sendTransaction is correct, why does MetaMask say 'likely to fail'?\n// Answer: The transaction IS failing on-chain simulation.\n// This means the calldata itself is wrong, OR the contract is reverting.\n\n// The RelayApprover contract requires specific conditions to approve.\n// If the quote is stale (>15 seconds old), the approval may revert.\n// The quote refetches every 15 seconds - but executeQuote uses the CACHED quote data.\n\nconsole.log('The issue is likely a stale quote or wrong approval parameters');\n\"",
      "description": "Analyze why approval transaction fails simulation"
    },
    "output": "The issue is likely a stale quote or wrong approval parameters\n",
    "metadata": {
      "output": "The issue is likely a stale quote or wrong approval parameters\n",
      "exit": 0,
      "description": "Analyze why approval transaction fails simulation"
    },
    "title": "node -e \"\n// So hexToBigInt('995010715204139091') === BigInt('995010715204139091') = true\n// That means viem's hexToBigInt actually handles decimal strings correctly for this case\n// The value field is fine. Let me check what the SDK does vs what we do\n\n// SDK: hexToBigInt(stepData.value || 0)  \n// Our code: hexToBigInt(((stepItem.data.value as string) || '0') as hex)\n\n// The issue must be something else. Let me check if the approval tx is failing\n// because of the 'to' address or 'data' field\n\n// What does the approval step look like?\n// 'to' = RelayApprover contract address\n// 'data' = encoded approve() call\n// 'value' = '0' (approvals don't send ETH)\n\n// If our sendTransaction is correct, why does MetaMask say 'likely to fail'?\n// Answer: The transaction IS failing on-chain simulation.\n// This means the calldata itself is wrong, OR the contract is reverting.\n\n// The RelayApprover contract requires specific conditions to approve.\n// If the quote is stale (>15 seconds old), the approval may revert.\n// The quote refetches every 15 seconds - but executeQuote uses the CACHED quote data.\n\nconsole.log('The issue is likely a stale quote or wrong approval parameters');\n\"",
    "time": {
      "start": 1772807049508,
      "end": 1772807049537
    }
  }
}