{
  "id": "prt_b740f1c63001eZZDN00rHDXulW",
  "messageID": "msg_b740e6bdd001wfzRmC5x7V6Ue6",
  "sessionID": "ses_48c2723c4ffemhO1dVP9NSYRB5",
  "type": "tool",
  "tool": "edit",
  "callID": "toolu_vrtx_01BFoXzKztuJrZoFLjRVoRJ2",
  "state": {
    "status": "completed",
    "input": {
      "filePath": "/home/user/sandbox/workspace/frontend/src/pages/RelaySwap.tsx",
      "oldString": "        return {\n          id: req.id,\n          fromToken: fromTokenAddress,\n          fromTokenSymbol: fromSymbol,\n          fromTokenDecimals: fromDecimals,\n          toToken: toTokenAddress,\n          toTokenSymbol: toSymbol,\n          toTokenDecimals: toDecimals,\n          fromAmount,\n          toAmount,\n          fromChain: originChain?.displayName || originChain?.name || 'Unknown',\n          fromChainId: originChainId || 0,\n          fromChainIcon: originChain?.iconUrl,\n          toChain: destChain?.displayName || destChain?.name || 'Unknown',\n          toChainId: destChainId || 0,\n          toChainIcon: destChain?.iconUrl,\n          status: req.status,\n          timestamp: createdTime,\n          completedAt,\n          txHash: req.data.outTxs?.[0]?.hash,\n          inTxHash: req.data.inTxs?.[0]?.hash,\n        }",
      "newString": "        return {\n          id: req.id,\n          type: transactionType,\n          fromToken: fromTokenAddress,\n          fromTokenSymbol: fromSymbol,\n          fromTokenDecimals: fromDecimals,\n          fromTokenLogo,\n          toToken: toTokenAddress,\n          toTokenSymbol: toSymbol,\n          toTokenDecimals: toDecimals,\n          toTokenLogo,\n          fromAmount,\n          toAmount,\n          fromChain: originChain?.displayName || originChain?.name || 'Unknown',\n          fromChainId: originChainId || 0,\n          fromChainIcon: originChain?.iconUrl,\n          toChain: destChain?.displayName || destChain?.name || 'Unknown',\n          toChainId: destChainId || 0,\n          toChainIcon: destChain?.iconUrl,\n          status: req.status,\n          timestamp: createdTime,\n          completedAt,\n          txHash: req.data.outTxs?.[0]?.hash,\n          inTxHash: req.data.inTxs?.[0]?.hash,\n          batchTokens: transactionType === 'batch' ? batchTokens : undefined,\n        }"
    },
    "output": "<system-reminder>CRITICAL: Make sure you read the hooks functionality and the functions they expose. DON'T MAKE ASSUMPTIONS</system-reminder><system-reminder>CRITICAL: Make sure you run the diagnostics tool when you're done with all the tasks.</system-reminder>",
    "metadata": {
      "diagnostics": {},
      "diff": "Index: /home/user/sandbox/workspace/frontend/src/pages/RelaySwap.tsx\n===================================================================\n--- /home/user/sandbox/workspace/frontend/src/pages/RelaySwap.tsx\n+++ /home/user/sandbox/workspace/frontend/src/pages/RelaySwap.tsx\n@@ -1668,14 +1668,17 @@\n   const completedAt = req.status === 'success' ? updatedTime : undefined\n   \n   return {\n     id: req.id,\n+    type: transactionType,\n     fromToken: fromTokenAddress,\n     fromTokenSymbol: fromSymbol,\n     fromTokenDecimals: fromDecimals,\n+    fromTokenLogo,\n     toToken: toTokenAddress,\n     toTokenSymbol: toSymbol,\n     toTokenDecimals: toDecimals,\n+    toTokenLogo,\n     fromAmount,\n     toAmount,\n     fromChain: originChain?.displayName || originChain?.name || 'Unknown',\n     fromChainId: originChainId || 0,\n@@ -1687,8 +1690,9 @@\n     timestamp: createdTime,\n     completedAt,\n     txHash: req.data.outTxs?.[0]?.hash,\n     inTxHash: req.data.inTxs?.[0]?.hash,\n+    batchTokens: transactionType === 'batch' ? batchTokens : undefined,\n   }\n }))\n \n setSwapHistory(history)\n"
    },
    "title": "frontend/src/pages/RelaySwap.tsx",
    "time": {
      "start": 1767178712696,
      "end": 1767178712701
    }
  }
}