{
  "id": "prt_c9b0c2685001kmRETf4L542nKN",
  "messageID": "msg_c9b0c0b75001feoaUl1k26Kepi",
  "sessionID": "ses_36508ab06ffeFm8HXnVC3yjmH2",
  "type": "tool",
  "tool": "read",
  "callID": "toolu_bdrk_011gtJCygVUQVqwDGwDHrxnE",
  "state": {
    "status": "completed",
    "input": {
      "filePath": "/home/user/sandbox/workspace/frontend/src/pages/RelaySwap.tsx",
      "offset": 3100,
      "limit": 100
    },
    "output": "<file>\n03101|                     <Button\n03102|                       variant=\"ghost\"\n03103|                       size=\"sm\"\n03104|                       className=\"h-6 text-xs px-2\"\n03105|                       onClick={() => {\n03106|                         const allSelected = batchTokens.every(t => t.selected !== false)\n03107|                         setBatchTokens(batchTokens.map(t => ({ ...t, selected: !allSelected })))\n03108|                       }}\n03109|                     >\n03110|                       {batchTokens.every(t => t.selected !== false) ? 'Deselect All' : 'Select All'}\n03111|                     </Button>\n03112|                   )}\n03113|                 </div>\n03114| \n03115|                 <ScrollArea className=\"h-48\">\n03116|                   <div className=\"space-y-1\">\n03117|                     {batchTokens.map((wt, i) => (\n03118|                       <div\n03119|                         key={`${wt.token.chainId}-${wt.token.address}-${i}`}\n03120|                         className={`flex items-center gap-2 p-2 border rounded cursor-pointer transition-colors ${wt.selected !== false ? 'border-accent/50 bg-accent/5' : 'border-border opacity-60'}`}\n03121|                         onClick={() => setBatchTokens(batchTokens.map((t, idx) => idx === i ? { ...t, selected: t.selected === false ? true : false } : t))}\n03122|                       >\n03123|                         <Checkbox\n03124|                           checked={wt.selected !== false}\n03125|                           onCheckedChange={() => setBatchTokens(batchTokens.map((t, idx) => idx === i ? { ...t, selected: t.selected === false ? true : false } : t))}\n03126|                           onClick={e => e.stopPropagation()}\n03127|                           className=\"flex-shrink-0\"\n03128|                         />\n03129|                         <TokenLogo\n03130|                           address={wt.token.metadata?.isNative || isNativeAddress(wt.token.address) ? undefined : wt.token.address}\n03131|                           chainId={wt.token.chainId}\n03132|                           symbol={wt.token.symbol}\n03133|                           logoURI={wt.token.metadata?.logoURI}\n03134|                           size={4}\n03135|                         />\n03136|                         <div className=\"flex-1 min-w-0\">\n03137|                           <div className=\"text-xs font-medium\">{wt.token.symbol}</div>\n03138|                           <div className=\"text-xs text-muted-foreground truncate\">{wt.token.name}</div>\n03139|                         </div>\n03140|                         <div className=\"text-right flex-shrink-0\">\n03141|                           <div className=\"text-xs font-medium\">{parseFloat(wt.balanceFormatted).toFixed(4)}</div>\n03142|                         </div>\n03143|                       </div>\n03144|                     ))}\n03145|                   </div>\n03146|                 </ScrollArea>\n03147| \n03148|                 <Button\n03149|                   variant=\"outline\"\n03150|                   size=\"sm\"\n03151|                   onClick={() => {\n03152|                     setSelectingFor('batch')\n03153|                     setIsTokenSelectOpen(true)\n03154|                   }}\n03155|                   className=\"w-full h-8 text-xs\"\n03156|                 >\n03157|                   Add Token\n03158|                 </Button>\n03159| \n03160|                 <Separator />\n03161| \n03162|                 <div className=\"space-y-2\">\n03163|                   <div className=\"text-xs text-muted-foreground\">{batchChain && toChain && batchChain.id !== toChain.id ? 'Bridge to' : 'Swap to'}</div>\n03164|                   <div className=\"flex gap-2\">\n03165|                     <Button\n03166|                       variant=\"outline\"\n03167|                       onClick={() => {\n03168|                         setSelectingFor('to')\n03169|                         setIsChainSelectOpen(true)\n03170|                       }}\n03171|                       className=\"flex-1 justify-between h-8 text-xs\"\n03172|                     >\n03173|                       <div className=\"flex items-center gap-1.5\">\n03174|                         {toChain?.iconUrl && (\n03175|                           <img src={toChain.iconUrl} alt=\"\" className=\"h-4 w-4 rounded-full\" />\n03176|                         )}\n03177|                         <span>{toChain?.displayName || 'Select'}</span>\n03178|                       </div>\n03179|                       <ChevronDown className=\"h-3 w-3\" />\n03180|                     </Button>\n03181|                     \n03182|                     <Button\n03183|                       variant=\"outline\"\n03184|                       onClick={() => {\n03185|                         setSelectingFor('to')\n03186|                         setIsTokenSelectOpen(true)\n03187|                       }}\n03188|                       className=\"flex-1 justify-between h-8 text-xs\"\n03189|                     >\n03190|                       <div className=\"flex items-center gap-1.5\">\n03191|                         {toToken && (\n03192|                           <TokenLogo address={toToken.metadata?.isNative || isNativeAddress(toToken.address) ? undefined : toToken.address} chainId={toToken.chainId} symbol={toToken.symbol} logoURI={toToken.metadata?.logoURI} size={4} />\n03193|                         )}\n03194|                         <span>{toToken?.symbol || 'Select'}</span>\n03195|                       </div>\n03196|                       <ChevronDown className=\"h-3 w-3\" />\n03197|                     </Button>\n03198|                   </div>\n03199|                 </div>\n03200| \n\n(File has more lines. Use 'offset' parameter to read beyond line 3200)\n</file>",
    "metadata": {
      "preview": "                    <Button\n                      variant=\"ghost\"\n                      size=\"sm\"\n                      className=\"h-6 text-xs px-2\"\n                      onClick={() => {\n                        const allSelected = batchTokens.every(t => t.selected !== false)\n                        setBatchTokens(batchTokens.map(t => ({ ...t, selected: !allSelected })))\n                      }}\n                    >\n                      {batchTokens.every(t => t.selected !== false) ? 'Deselect All' : 'Select All'}\n                    </Button>\n                  )}\n                </div>\n\n                <ScrollArea className=\"h-48\">\n                  <div className=\"space-y-1\">\n                    {batchTokens.map((wt, i) => (\n                      <div\n                        key={`${wt.token.chainId}-${wt.token.address}-${i}`}\n                        className={`flex items-center gap-2 p-2 border rounded cursor-pointer transition-colors ${wt.selected !== false ? 'border-accent/50 bg-accent/5' : 'border-border opacity-60'}`}"
    },
    "title": "frontend/src/pages/RelaySwap.tsx",
    "time": {
      "start": 1772127791419,
      "end": 1772127791422
    }
  }
}